disell/SegmentationDataset.py
disell/__init__.py
disell/_flood_fill.cpython-314-x86_64-linux-gnu.so
disell/flood_fill_probabilities.py
disell/registration.py
disell/segmentation_module.py
disell-0.1.11.dist-info/METADATA
disell-0.1.11.dist-info/WHEEL
disell-0.1.11.dist-info/RECORD
disell-0.1.11.dist-info/licenses/LICENSE
