Metadata-Version: 2.2
Name: disell
Version: 0.1.11
Summary: disell package with C++ speedup
Author-Email: Johann Haack <johaac@dtu.dk>
Project-URL: Documentation, https://disell.readthedocs.io/
Requires-Python: >=3.8
